[
  {
    "word": "Office",
    "word_count": 2005
  },
  {
    "word": "Resources",
    "word_count": 1684
  },
  {
    "word": "Human",
    "word_count": 1658
  },
  {
    "word": "OHRM",
    "word_count": 1654
  },
  {
    "word": "Schedules",
    "word_count": 1650
  },
  {
    "word": "Care",
    "word_count": 1534
  },
  {
    "word": "Strategic",
    "word_count": 1430
  },
  {
    "word": "Analytics",
    "word_count": 1430
  },
  {
    "word": "Improvement",
    "word_count": 1430
  },
  {
    "word": "Learning",
    "word_count": 1430
  },
  {
    "word": "SAIL",
    "word_count": 1430
  },
  {
    "word": "Quality",
    "word_count": 1430
  },
  {
    "word": "Benefits",
    "word_count": 715
  },
  {
    "word": "Claims",
    "word_count": 696
  },
  {
    "word": "Hospital",
    "word_count": 511
  },
  {
    "word": "Performance",
    "word_count": 506
  },
  {
    "word": "National",
    "word_count": 373
  },
  {
    "word": "Analysis",
    "word_count": 360
  },
  {
    "word": "Statistics",
    "word_count": 360
  },
  {
    "word": "Acquisition",
    "word_count": 232
  },
  {
    "word": "Logistics",
    "word_count": 199
  },
  {
    "word": "FOIA",
    "word_count": 186
  },
  {
    "word": "Archive",
    "word_count": 141
  },
  {
    "word": "Freedom",
    "word_count": 105
  },
  {
    "word": "Requests",
    "word_count": 105
  },
  {
    "word": "Expenditures",
    "word_count": 100
  },
  {
    "word": "Home",
    "word_count": 95
  },
  {
    "word": "General",
    "word_count": 71
  },
  {
    "word": "Reporting",
    "word_count": 69
  },
  {
    "word": "Procurement",
    "word_count": 54
  },
  {
    "word": "OPAL",
    "word_count": 54
  },
  {
    "word": "Veteran",
    "word_count": 54
  },
  {
    "word": "Population",
    "word_count": 50
  },
  {
    "word": "Utilization",
    "word_count": 45
  },
  {
    "word": "Loans",
    "word_count": 45
  },
  {
    "word": "Services",
    "word_count": 43
  },
  {
    "word": "Freight",
    "word_count": 40
  },
  {
    "word": "FEAR",
    "word_count": 40
  },
  {
    "word": "Complaints",
    "word_count": 40
  },
  {
    "word": "Resolution",
    "word_count": 40
  },
  {
    "word": "Medical",
    "word_count": 38
  },
  {
    "word": "Community",
    "word_count": 38
  },
  {
    "word": "Health",
    "word_count": 38
  },
  {
    "word": "Training",
    "word_count": 38
  },
  {
    "word": "Payment",
    "word_count": 35
  },
  {
    "word": "Rate",
    "word_count": 35
  },
  {
    "word": "Burial",
    "word_count": 35
  },
  {
    "word": "Flags",
    "word_count": 35
  },
  {
    "word": "Diem",
    "word_count": 35
  },
  {
    "word": "Academy",
    "word_count": 33
  },
  {
    "word": "VAAA",
    "word_count": 33
  },
  {
    "word": "Geriatrics",
    "word_count": 30
  },
  {
    "word": "Extended",
    "word_count": 30
  },
  {
    "word": "Privacy",
    "word_count": 30
  },
  {
    "word": "Innovation",
    "word_count": 27
  },
  {
    "word": "Construction",
    "word_count": 27
  },
  {
    "word": "Facilities",
    "word_count": 27
  },
  {
    "word": "Counsel",
    "word_count": 25
  },
  {
    "word": "Compensation",
    "word_count": 23
  },
  {
    "word": "Bills",
    "word_count": 20
  },
  {
    "word": "Finance",
    "word_count": 20
  },
  {
    "word": "Surveys",
    "word_count": 20
  },
  {
    "word": "Subrogation",
    "word_count": 20
  },
  {
    "word": "Request",
    "word_count": 20
  },
  {
    "word": "VALERI",
    "word_count": 18
  },
  {
    "word": "Loan",
    "word_count": 18
  },
  {
    "word": "Education",
    "word_count": 17
  },
  {
    "word": "Cost",
    "word_count": 16
  },
  {
    "word": "Employment",
    "word_count": 16
  },
  {
    "word": "Fiscal",
    "word_count": 15
  },
  {
    "word": "ArchitectEngineer",
    "word_count": 15
  },
  {
    "word": "Healthcare",
    "word_count": 14
  },
  {
    "word": "Research",
    "word_count": 13
  },
  {
    "word": "Vocational",
    "word_count": 13
  },
  {
    "word": "Rehabilitation",
    "word_count": 13
  },
  {
    "word": "VR&E",
    "word_count": 13
  },
  {
    "word": "Homeless",
    "word_count": 13
  },
  {
    "word": "Volume",
    "word_count": 13
  },
  {
    "word": "Records",
    "word_count": 12
  },
  {
    "word": "Life",
    "word_count": 11
  },
  {
    "word": "Insurance",
    "word_count": 11
  },
  {
    "word": "American",
    "word_count": 11
  },
  {
    "word": "High",
    "word_count": 10
  },
  {
    "word": "Related",
    "word_count": 10
  },
  {
    "word": "Tech",
    "word_count": 10
  },
  {
    "word": "Sites",
    "word_count": 10
  },
  {
    "word": "Equipment",
    "word_count": 10
  },
  {
    "word": "Summary",
    "word_count": 10
  },
  {
    "word": "XIII",
    "word_count": 10
  },
  {
    "word": "Accounting",
    "word_count": 10
  },
  {
    "word": "EnhancedUse",
    "word_count": 10
  },
  {
    "word": "Lease",
    "word_count": 10
  },
  {
    "word": "Transition",
    "word_count": 9
  },
  {
    "word": "Electronic",
    "word_count": 9
  },
  {
    "word": "Teams",
    "word_count": 9
  },
  {
    "word": "Report",
    "word_count": 9
  },
  {
    "word": "Interface",
    "word_count": 9
  },
  {
    "word": "Returning",
    "word_count": 9
  },
  {
    "word": "Members",
    "word_count": 9
  },
  {
    "word": "OEFOIFOND",
    "word_count": 9
  },
  {
    "word": "Servicers",
    "word_count": 9
  }
]
