[
  {
    "word": "Hospital",
    "word_count": 1078
  },
  {
    "word": "Performance",
    "word_count": 1030
  },
  {
    "word": "System",
    "word_count": 854
  },
  {
    "word": "Health",
    "word_count": 752
  },
  {
    "word": "Center",
    "word_count": 684
  },
  {
    "word": "Care",
    "word_count": 670
  },
  {
    "word": "Medical",
    "word_count": 634
  },
  {
    "word": "Veterans",
    "word_count": 370
  },
  {
    "word": "Service",
    "word_count": 256
  },
  {
    "word": "Healthcare",
    "word_count": 206
  },
  {
    "word": "FOIA",
    "word_count": 180
  },
  {
    "word": "Report",
    "word_count": 132
  },
  {
    "word": "Home",
    "word_count": 126
  },
  {
    "word": "Education",
    "word_count": 94
  },
  {
    "word": "American",
    "word_count": 80
  },
  {
    "word": "Recovery",
    "word_count": 80
  },
  {
    "word": "Reinvestment",
    "word_count": 80
  },
  {
    "word": "Center",
    "word_count": 78
  },
  {
    "word": "Training",
    "word_count": 72
  },
  {
    "word": "Texas",
    "word_count": 72
  },
  {
    "word": "Central",
    "word_count": 70
  },
  {
    "word": "City",
    "word_count": 64
  },
  {
    "word": "Feed",
    "word_count": 62
  },
  {
    "word": "Veteran",
    "word_count": 60
  },
  {
    "word": "Louis",
    "word_count": 56
  },
  {
    "word": "National",
    "word_count": 56
  },
  {
    "word": "Memorial",
    "word_count": 54
  },
  {
    "word": "Alabama",
    "word_count": 54
  },
  {
    "word": "Junction",
    "word_count": 54
  },
  {
    "word": "Access",
    "word_count": 52
  },
  {
    "word": "COIN",
    "word_count": 52
  },
  {
    "word": "Valley",
    "word_count": 48
  },
  {
    "word": "Providence",
    "word_count": 48
  },
  {
    "word": "Iowa",
    "word_count": 46
  },
  {
    "word": "Life",
    "word_count": 46
  },
  {
    "word": "Annual",
    "word_count": 46
  },
  {
    "word": "Eastern",
    "word_count": 42
  },
  {
    "word": "Finance",
    "word_count": 42
  },
  {
    "word": "Faith",
    "word_count": 40
  },
  {
    "word": "Opportunity",
    "word_count": 40
  },
  {
    "word": "Initaitves",
    "word_count": 40
  },
  {
    "word": "Kansas",
    "word_count": 40
  },
  {
    "word": "Program",
    "word_count": 38
  },
  {
    "word": "Management",
    "word_count": 36
  },
  {
    "word": "Indiana",
    "word_count": 36
  },
  {
    "word": "VAMC",
    "word_count": 36
  },
  {
    "word": "Summary",
    "word_count": 36
  },
  {
    "word": "Mountain",
    "word_count": 36
  },
  {
    "word": "Local",
    "word_count": 36
  },
  {
    "word": "Features",
    "word_count": 36
  },
  {
    "word": "Birmingham",
    "word_count": 36
  },
  {
    "word": "Grand",
    "word_count": 36
  },
  {
    "word": "Compensation",
    "word_count": 34
  },
  {
    "word": "Whole",
    "word_count": 34
  },
  {
    "word": "Amarillo",
    "word_count": 34
  },
  {
    "word": "Patient",
    "word_count": 34
  },
  {
    "word": "Women",
    "word_count": 32
  },
  {
    "word": "Altoona",
    "word_count": 32
  },
  {
    "word": "Arbor",
    "word_count": 32
  },
  {
    "word": "Fayetteville",
    "word_count": 32
  },
  {
    "word": "Overton",
    "word_count": 30
  },
  {
    "word": "Johnson",
    "word_count": 30
  },
  {
    "word": "Hudson",
    "word_count": 30
  },
  {
    "word": "Network",
    "word_count": 30
  },
  {
    "word": "Orlando",
    "word_count": 30
  },
  {
    "word": "Benefits",
    "word_count": 30
  },
  {
    "word": "Dayton",
    "word_count": 30
  },
  {
    "word": "Memphis",
    "word_count": 30
  },
  {
    "word": "Hunter",
    "word_count": 30
  },
  {
    "word": "Holmes",
    "word_count": 30
  },
  {
    "word": "Volume",
    "word_count": 30
  },
  {
    "word": "McGuire",
    "word_count": 30
  },
  {
    "word": "Richmond",
    "word_count": 30
  },
  {
    "word": "Travel",
    "word_count": 30
  },
  {
    "word": "Northern",
    "word_count": 30
  },
  {
    "word": "Office",
    "word_count": 30
  },
  {
    "word": "Fiscal",
    "word_count": 30
  },
  {
    "word": "Year",
    "word_count": 30
  },
  {
    "word": "West",
    "word_count": 30
  },
  {
    "word": "James",
    "word_count": 28
  },
  {
    "word": "Regulations",
    "word_count": 28
  },
  {
    "word": "Mexico",
    "word_count": 28
  },
  {
    "word": "Salem",
    "word_count": 28
  },
  {
    "word": "Poplar",
    "word_count": 26
  },
  {
    "word": "Bluff",
    "word_count": 26
  },
  {
    "word": "Danville",
    "word_count": 26
  },
  {
    "word": "Paso",
    "word_count": 26
  },
  {
    "word": "Library",
    "word_count": 26
  },
  {
    "word": "STVHCS",
    "word_count": 24
  },
  {
    "word": "MannGrandstaff",
    "word_count": 24
  },
  {
    "word": "Black",
    "word_count": 24
  },
  {
    "word": "Insurance",
    "word_count": 24
  },
  {
    "word": "Hills",
    "word_count": 24
  },
  {
    "word": "Leavenworth",
    "word_count": 24
  },
  {
    "word": "Nevada",
    "word_count": 24
  },
  {
    "word": "County",
    "word_count": 24
  },
  {
    "word": "Acquisition",
    "word_count": 24
  },
  {
    "word": "Minneapolis",
    "word_count": 24
  },
  {
    "word": "Milwaukee",
    "word_count": 24
  },
  {
    "word": "Academy",
    "word_count": 24
  },
  {
    "word": "Ohio",
    "word_count": 24
  },
  {
    "word": "VAAA",
    "word_count": 24
  },
  {
    "word": "Franchise",
    "word_count": 24
  },
  {
    "word": "Diego",
    "word_count": 24
  },
  {
    "word": "Fund",
    "word_count": 24
  },
  {
    "word": "Minority",
    "word_count": 24
  },
  {
    "word": "Safety",
    "word_count": 24
  },
  {
    "word": "John",
    "word_count": 24
  },
  {
    "word": "Rehabilitation",
    "word_count": 24
  },
  {
    "word": "MIRECC",
    "word_count": 24
  },
  {
    "word": "Palm",
    "word_count": 24
  },
  {
    "word": "Connecticut",
    "word_count": 22
  },
  {
    "word": "Energy",
    "word_count": 22
  },
  {
    "word": "White",
    "word_count": 22
  },
  {
    "word": "EMPS",
    "word_count": 22
  },
  {
    "word": "Angeles",
    "word_count": 22
  },
  {
    "word": "Administration",
    "word_count": 22
  },
  {
    "word": "Cloud",
    "word_count": 22
  },
  {
    "word": "Cheyenne",
    "word_count": 22
  },
  {
    "word": "Francisco",
    "word_count": 22
  },
  {
    "word": "Wait",
    "word_count": 22
  },
  {
    "word": "Federal",
    "word_count": 20
  },
  {
    "word": "Audit",
    "word_count": 20
  },
  {
    "word": "Puget",
    "word_count": 20
  },
  {
    "word": "Sound",
    "word_count": 20
  },
  {
    "word": "Coverage",
    "word_count": 18
  },
  {
    "word": "Fargo",
    "word_count": 18
  },
  {
    "word": "Loma",
    "word_count": 18
  },
  {
    "word": "Linda",
    "word_count": 18
  },
  {
    "word": "Michigan",
    "word_count": 18
  },
  {
    "word": "Harbor",
    "word_count": 18
  },
  {
    "word": "Duty",
    "word_count": 18
  },
  {
    "word": "Appointments",
    "word_count": 18
  },
  {
    "word": "Washington",
    "word_count": 18
  },
  {
    "word": "Canandaigua",
    "word_count": 18
  },
  {
    "word": "Beckley",
    "word_count": 18
  },
  {
    "word": "Beach",
    "word_count": 18
  },
  {
    "word": "Edith",
    "word_count": 18
  },
  {
    "word": "NVSBE",
    "word_count": 18
  },
  {
    "word": "Cleveland",
    "word_count": 18
  },
  {
    "word": "EMPLOYEES",
    "word_count": 18
  },
  {
    "word": "Pines",
    "word_count": 18
  },
  {
    "word": "Marion",
    "word_count": 18
  },
  {
    "word": "Nourse",
    "word_count": 18
  },
  {
    "word": "OCCUPATION",
    "word_count": 18
  },
  {
    "word": "Butler",
    "word_count": 18
  },
  {
    "word": "CAVHCS",
    "word_count": 18
  },
  {
    "word": "Rogers",
    "word_count": 18
  },
  {
    "word": "River",
    "word_count": 18
  },
  {
    "word": "William",
    "word_count": 18
  },
  {
    "word": "Georgia",
    "word_count": 18
  },
  {
    "word": "Sierra",
    "word_count": 18
  },
  {
    "word": "Vermont",
    "word_count": 18
  },
  {
    "word": "Middleton",
    "word_count": 18
  },
  {
    "word": "Prosthetic",
    "word_count": 18
  },
  {
    "word": "Clinical",
    "word_count": 18
  },
  {
    "word": "Palo",
    "word_count": 18
  },
  {
    "word": "Hampton",
    "word_count": 18
  },
  {
    "word": "Services",
    "word_count": 18
  },
  {
    "word": "Alto",
    "word_count": 18
  },
  {
    "word": "Pension",
    "word_count": 18
  },
  {
    "word": "Western",
    "word_count": 18
  },
  {
    "word": "Tomah",
    "word_count": 18
  },
  {
    "word": "Ozarks",
    "word_count": 18
  },
  {
    "word": "Oklahoma",
    "word_count": 18
  },
  {
    "word": "Members",
    "word_count": 18
  },
  {
    "word": "Veterans&#",
    "word_count": 18
  },
  {
    "word": "Sheridan",
    "word_count": 18
  },
  {
    "word": "Phoenix",
    "word_count": 18
  },
  {
    "word": "Roseburg",
    "word_count": 18
  },
  {
    "word": "Arizona",
    "word_count": 18
  },
  {
    "word": "Rocky",
    "word_count": 18
  },
  {
    "word": "Southern",
    "word_count": 18
  },
  {
    "word": "Island",
    "word_count": 18
  },
  {
    "word": "Walla",
    "word_count": 16
  },
  {
    "word": "Receiving",
    "word_count": 16
  },
  {
    "word": "Salt",
    "word_count": 16
  },
  {
    "word": "Lake",
    "word_count": 16
  },
  {
    "word": "Miami",
    "word_count": 16
  },
  {
    "word": "Brooklyn",
    "word_count": 16
  },
  {
    "word": "Alaska",
    "word_count": 16
  },
  {
    "word": "Boston",
    "word_count": 16
  },
  {
    "word": "Jersey",
    "word_count": 16
  },
  {
    "word": "Portland",
    "word_count": 16
  },
  {
    "word": "Profile",
    "word_count": 16
  },
  {
    "word": "Times",
    "word_count": 16
  },
  {
    "word": "Fact",
    "word_count": 16
  },
  {
    "word": "Based",
    "word_count": 14
  },
  {
    "word": "VistA",
    "word_count": 14
  },
  {
    "word": "Programs",
    "word_count": 14
  },
  {
    "word": "During",
    "word_count": 14
  },
  {
    "word": "Albany",
    "word_count": 14
  },
  {
    "word": "Harry",
    "word_count": 12
  },
  {
    "word": "Nashville",
    "word_count": 12
  },
  {
    "word": "Bath",
    "word_count": 12
  },
  {
    "word": "Suicide",
    "word_count": 12
  },
  {
    "word": "Distribution",
    "word_count": 12
  },
  {
    "word": "Atlanta",
    "word_count": 12
  },
  {
    "word": "Technology",
    "word_count": 12
  },
  {
    "word": "Hines",
    "word_count": 12
  },
  {
    "word": "Detroit",
    "word_count": 12
  },
  {
    "word": "Truman",
    "word_count": 12
  },
  {
    "word": "Active",
    "word_count": 12
  },
  {
    "word": "Jennings",
    "word_count": 12
  },
  {
    "word": "Coastal",
    "word_count": 12
  },
  {
    "word": "Honolulu",
    "word_count": 12
  },
  {
    "word": "Review",
    "word_count": 12
  },
  {
    "word": "Prevention",
    "word_count": 12
  },
  {
    "word": "Completed",
    "word_count": 12
  },
  {
    "word": "Expenditures",
    "word_count": 12
  },
  {
    "word": "Reference",
    "word_count": 12
  },
  {
    "word": "Pershing",
    "word_count": 12
  },
  {
    "word": "Cincinnati",
    "word_count": 12
  },
  {
    "word": "Bryan",
    "word_count": 12
  },
  {
    "word": "Bend",
    "word_count": 12
  },
  {
    "word": "Long",
    "word_count": 12
  },
  {
    "word": "Model",
    "word_count": 12
  },
  {
    "word": "Reserve",
    "word_count": 12
  },
  {
    "word": "Stokes",
    "word_count": 12
  },
  {
    "word": "Tucson",
    "word_count": 12
  },
  {
    "word": "Dorn",
    "word_count": 12
  },
  {
    "word": "Highlights",
    "word_count": 12
  },
  {
    "word": "Perry",
    "word_count": 12
  },
  {
    "word": "Veterans&#",
    "word_count": 12
  },
  {
    "word": "Montana",
    "word_count": 12
  },
  {
    "word": "Point",
    "word_count": 12
  },
  {
    "word": "Website",
    "word_count": 12
  },
  {
    "word": "NebraskaWestern",
    "word_count": 12
  },
  {
    "word": "Martinsburg",
    "word_count": 12
  },
  {
    "word": "Expenditure",
    "word_count": 12
  },
  {
    "word": "List",
    "word_count": 12
  },
  {
    "word": "Coatesville",
    "word_count": 12
  },
  {
    "word": "VADoD",
    "word_count": 12
  },
  {
    "word": "Pacific",
    "word_count": 12
  },
  {
    "word": "Syracuse",
    "word_count": 12
  }
]
